{
  "group": {
    "id": "broker0-{row}-{column}",
    "transform": {
      "translateX": 600,
      "translateY": 100
    },
    "width": 20,
    "height": 28
  },
  "shape": {
    "type": "rect",
    "attributes": {
      "x": 10,
      "y": 10
    },
    "matrix": {
      "row": {
        "count": 3,
        "offset": 50
      },
      "column": {
        "count": 6,
        "offset": 20
      }
    }
  },
  "label": {
    "text": "{}",
    "attributes": {
      "x": 16,
      "y": 8
    }
  }
}